TerminalButtons.py
TerminalButtons-1.0.0.dist-info/METADATA
TerminalButtons-1.0.0.dist-info/WHEEL
TerminalButtons-1.0.0.dist-info/top_level.txt
TerminalButtons-1.0.0.dist-info/RECORD
