Metadata-Version: 2.1
Name: TerminalButtons
Version: 1.0.0
Summary: Buttons in Linux terminal
Home-page: https://github.com/Peticali/TerminalButtons
Author: Peticali
Author-email: pedropalmeira68@gmail.com
License: MIT
Platform: UNKNOWN
